<?xml version='1.0' encoding='utf-8'?>
<product>
  <name>Кронштейн TIANDY DF20Y</name>
  <model>DF20Y</model>
  <sku>86</sku>
  <brand>Tiandy</brand>
  <category>Аксессуары</category>
  <subcategory />
  <price>0</price>
  <product_url>https://tiandy-russia.ru/aksessuary/kronshteyn-tiandy-df20y-86/</product_url>
  <description>
    <paragraph>Настенный Г-образный кронштейн DF20Y TIANDY для камер PTZ</paragraph>
  </description>
  <specifications />
  <files>
    <image>image.jpg</image>
  </files>
  <documents />
</product>