<?xml version='1.0' encoding='utf-8'?>
<product>
  <name>Кронштейн (Пластик) TIANDY A28</name>
  <model>A28</model>
  <sku>84</sku>
  <brand>Tiandy</brand>
  <category>Аксессуары</category>
  <subcategory />
  <price>1490</price>
  <product_url>https://tiandy-russia.ru/aksessuary/kronshteyn-plastik-tiandy-a28-84/</product_url>
  <description>
    <paragraph>Настенное крепление A28  TIANDY для моториз. купольных камер M, S серий, мини PTZ камер</paragraph>
  </description>
  <specifications />
  <files>
    <image>image.jpg</image>
    <image>image_2.jpg</image>
  </files>
  <documents />
</product>