<?xml version='1.0' encoding='utf-8'?>
<product>
  <name>DS-PR1-WE</name>
  <model>DS-PR1-WE</model>
  <category>Охранно-пожарная сигнализация</category>
  <subcategory />
  <product_url>https://hiwatch.net/-ds-pr1-we</product_url>
  <description>
    <paragraph>Ретранслятор DS-PR1-WE является беспроводным ретранслятором с поддержкой беспроводной связи 868 МГц, беспроводными протоколами Tri-X и Cam-X, несколькими методами регистрации, двусторонней беспроводной связью, автоматическим подключением. Ретранслятор используется для увеличения дальности РЧ-канала при передаче тревожного события.Беспроводной ретранстлятор для панели AX PRO</paragraph>
    <paragraph>Ретранслятор беспроводным с поддержкой беспроводной связи 868 МГц, беспроводными протоколами Tri-X</paragraph>
    <paragraph>и Cam-X, Ретранслятор используется для увеличения дальности РЧ-канала при передаче тревожного события. Увеличение связь TRI-X до 2000м, увеличение связь CAM-X до 800м; Поддерживается 4 ретранслятора на 1 охранную панель AX PRO; Автоматическое подключение датчиков к системе; АС от 100 до 240В; Резервное питание до 35 часов, встроенная литиевая батарея; Рабочая температура от -10 до 55 ; вес 372г; Размеры 150   150   25 мм; Установка на стену, внутри помещений;</paragraph>
  </description>
  <specifications>
    <spec>
      <name />
      <value>Ретранслятор беспроводным с поддержкой беспроводной связи 868 МГц, беспроводными протоколами Tri-X</value>
    </spec>
    <spec>
      <name />
      <value>и Cam-X, Ретранслятор используется для увеличения дальности РЧ-канала при передаче тревожного события. Увеличение связь TRI-X до 2000м, увеличение связь CAM-X до 800м</value>
    </spec>
    <spec>
      <name />
      <value>Поддерживается 4 ретранслятора на 1 охранную панель AX PRO</value>
    </spec>
    <spec>
      <name />
      <value>Автоматическое подключение датчиков к системе</value>
    </spec>
    <spec>
      <name />
      <value>АС от 100 до 240В</value>
    </spec>
    <spec>
      <name />
      <value>Резервное питание до 35 часов, встроенная литиевая батарея</value>
    </spec>
    <spec>
      <name />
      <value>Рабочая температура от -10 до 55</value>
    </spec>
    <spec>
      <name />
      <value>вес 372г</value>
    </spec>
    <spec>
      <name />
      <value>Размеры 150   150   25 мм</value>
    </spec>
    <spec>
      <name />
      <value>Установка на стену, внутри помещений</value>
    </spec>
  </specifications>
  <files>
    <image>image.jpg</image>
    <passport>passport.pdf</passport>
  </files>
</product>